ntgen/__init__.py
ntgen/__main__.py
ntgen/config.py
ntgen/exception.py
ntgen/main.py
ntgen/models.py
ntgen/ntgen.py
ntgen/render.py
ntgen/utils.py
ntgen-0.3.1.dist-info/entry_points.txt
ntgen-0.3.1.dist-info/LICENSE
ntgen-0.3.1.dist-info/WHEEL
ntgen-0.3.1.dist-info/METADATA
ntgen-0.3.1.dist-info/RECORD
