Metadata-Version: 2.1
Name: ntgen
Version: 0.3.1
Summary: named tuple generator
License: MIT
Author: Maciej Rapacz
Author-email: mmrapacz@protonmail.ch
Requires-Python: >=3.7,<4.0
Classifier: License :: OSI Approved :: MIT License
Classifier: Programming Language :: Python :: 3
Classifier: Programming Language :: Python :: 3.7
Classifier: Programming Language :: Python :: 3.8
Classifier: Programming Language :: Python :: 3.9
Requires-Dist: pyannotate (>=1.2.0,<2.0.0)
